shashvault/__init__.py
shashvault/main.py
shashvault-0.1.4.dist-info/licenses/LICENSE
shashvault-0.1.4.dist-info/METADATA
shashvault-0.1.4.dist-info/WHEEL
shashvault-0.1.4.dist-info/entry_points.txt
shashvault-0.1.4.dist-info/top_level.txt
shashvault-0.1.4.dist-info/RECORD
