Metadata-Version: 2.4
Name: shashvault
Version: 0.1.4
Summary: search Hashicorp vault path and secret
Home-page: https://gitlab.esss.lu.se/ics-infrastructure/shashvault
Author: Remy Mudingay
Author-email: remy.mudingay@ess.eu
License: BSD
Classifier: Programming Language :: Python :: 3
Classifier: License :: OSI Approved :: BSD License
Classifier: Operating System :: OS Independent
License-File: LICENSE
Requires-Dist: aiohttp~=3.8.4
Requires-Dist: requests~=2.28.1
Dynamic: author
Dynamic: author-email
Dynamic: classifier
Dynamic: description
Dynamic: description-content-type
Dynamic: home-page
Dynamic: license
Dynamic: license-file
Dynamic: requires-dist
Dynamic: summary
